PDFPro/__init__.py
PDFPro/info.py
PDFPro-0.0.9.dist-info/METADATA
PDFPro-0.0.9.dist-info/WHEEL
PDFPro-0.0.9.dist-info/top_level.txt
PDFPro-0.0.9.dist-info/RECORD
